mathcalc/__init__.py
mathcalculate-0.0.1.dist-info/LICENSE
mathcalculate-0.0.1.dist-info/METADATA
mathcalculate-0.0.1.dist-info/WHEEL
mathcalculate-0.0.1.dist-info/top_level.txt
mathcalculate-0.0.1.dist-info/RECORD
