Metadata-Version: 2.1
Name: mathcalculate
Version: 0.0.1
Summary: A small example package
Author-email: Mani Arasteh <mani.arasteh92@gmail.com>
Project-URL: Homepage, https://github.com/ManiArasteh/mathcalc
Project-URL: Issues, https://github.com/ManiArasteh/mathcalc/issues
Classifier: Programming Language :: Python :: 3
Classifier: License :: OSI Approved :: MIT License
Classifier: Operating System :: OS Independent
Requires-Python: >=3.9
License-File: LICENSE
